themis.finals.checker.result-1.1.0-py3.5-nspkg.pth
themis/finals/checker/result/__about__.py
themis/finals/checker/result/__init__.py
themis.finals.checker.result-1.1.0.dist-info/METADATA
themis.finals.checker.result-1.1.0.dist-info/RECORD
themis.finals.checker.result-1.1.0.dist-info/WHEEL
themis.finals.checker.result-1.1.0.dist-info/namespace_packages.txt
themis.finals.checker.result-1.1.0.dist-info/top_level.txt
