Metadata-Version: 2.1
Name: themis.finals.checker.result
Version: 1.1.0
Summary: Themis Finals checker result constants
Home-page: https://github.com/themis-project/themis-finals-checker-result-py
Author: Alexander Pyatkin
Author-email: aspyatkin@gmail.com
License: MIT
Platform: UNKNOWN
Requires-Dist: setuptools (>=35.0.0)
Requires-Dist: enum34 (>=1.1.6); python_version<"3.4"
